{
  "version": 1,
  "bugs": [
    {
      "id": "bug-001",
      "timestamp": "2026-07-14T12:27:44.582Z",
      "error_message": "Incorrect value in code",
      "file": "package.json",
      "root_cause": "Had \"eslint\"",
      "fix": "Changed to \"next lint\"",
      "tags": [
        "auto-detected",
        "wrong-value",
        "json"
      ],
      "related_bugs": [],
      "occurrences": 1,
      "last_seen": "2026-07-14T12:27:44.582Z"
    },
    {
      "id": "bug-002",
      "timestamp": "2026-07-14T12:28:17.928Z",
      "error_message": "Type error",
      "file": "drizzle.config.ts",
      "root_cause": "Missing or incorrect type annotation",
      "fix": "Added type assertion/annotation",
      "tags": [
        "auto-detected",
        "type-fix",
        "ts"
      ],
      "related_bugs": [],
      "occurrences": 1,
      "last_seen": "2026-07-14T12:28:17.928Z"
    },
    {
      "id": "bug-003",
      "timestamp": "2026-07-14T12:35:40.309Z",
      "error_message": "Significant refactor of ",
      "file": "prisma/schema.prisma",
      "root_cause": "3 lines replaced/restructured",
      "fix": "Rewrote 5→3 lines (3 removed)",
      "tags": [
        "auto-detected",
        "refactor",
        "prisma"
      ],
      "related_bugs": [],
      "occurrences": 1,
      "last_seen": "2026-07-14T12:35:40.309Z"
    },
    {
      "id": "bug-004",
      "timestamp": "2026-07-14T12:42:47.227Z",
      "error_message": "CSS fix: --font-sans",
      "file": "app/globals.css",
      "root_cause": "--font-sans: var(--font-geist-sans) → var(--font-sans)",
      "fix": "Changed --font-sans: var(--font-geist-sans) → var(--font-sans)",
      "tags": [
        "auto-detected",
        "style-fix",
        "css"
      ],
      "related_bugs": [],
      "occurrences": 2,
      "last_seen": "2026-07-14T12:42:53.352Z"
    },
    {
      "id": "bug-005",
      "timestamp": "2026-07-14T12:44:14.539Z",
      "error_message": "Wrong reference: injected should be CreateSchema",
      "file": "prisma/migrations/0000_init/migration.sql",
      "root_cause": "Used \"injected\" instead of \"CreateSchema\"",
      "fix": "Changed injected → CreateSchema",
      "tags": [
        "auto-detected",
        "wrong-reference",
        "sql"
      ],
      "related_bugs": [],
      "occurrences": 1,
      "last_seen": "2026-07-14T12:44:14.539Z"
    },
    {
      "id": "bug-006",
      "timestamp": "2026-07-14T12:59:39.688Z",
      "error_message": "Incorrect value in code",
      "file": "package.json",
      "root_cause": "Had \"test\"",
      "fix": "Changed to \"db:seed\"",
      "tags": [
        "auto-detected",
        "wrong-value",
        "json"
      ],
      "related_bugs": [],
      "occurrences": 1,
      "last_seen": "2026-07-14T12:59:39.688Z"
    },
    {
      "id": "bug-007",
      "timestamp": "2026-07-14T13:05:42.246Z",
      "error_message": "Significant refactor of ",
      "file": "prisma/schema.prisma",
      "root_cause": "5 lines replaced/restructured",
      "fix": "Rewrote 6→7 lines (5 removed)",
      "tags": [
        "auto-detected",
        "refactor",
        "prisma"
      ],
      "related_bugs": [],
      "occurrences": 1,
      "last_seen": "2026-07-14T13:05:42.246Z"
    },
    {
      "id": "bug-008",
      "timestamp": "2026-07-14T13:07:27.429Z",
      "error_message": "Significant refactor of ",
      "file": "lib/auth.ts",
      "root_cause": "27 lines replaced/restructured",
      "fix": "Rewrote 46→22 lines (27 removed)",
      "tags": [
        "auto-detected",
        "refactor",
        "ts"
      ],
      "related_bugs": [],
      "occurrences": 1,
      "last_seen": "2026-07-14T13:07:27.429Z"
    },
    {
      "id": "bug-009",
      "timestamp": "2026-07-14T13:10:41.029Z",
      "error_message": "Significant refactor of ",
      "file": "README.md",
      "root_cause": "4 lines replaced/restructured",
      "fix": "Rewrote 14→22 lines (4 removed)",
      "tags": [
        "auto-detected",
        "refactor",
        "md"
      ],
      "related_bugs": [],
      "occurrences": 1,
      "last_seen": "2026-07-14T13:10:41.029Z"
    },
    {
      "id": "bug-010",
      "timestamp": "2026-07-14T13:31:44.331Z",
      "error_message": "Incorrect value in code",
      "file": "app/page.tsx",
      "root_cause": "Had \"./sign-out-button\"",
      "fix": "Changed to \"@/components/sign-out-button\"",
      "tags": [
        "auto-detected",
        "wrong-value",
        "tsx"
      ],
      "related_bugs": [],
      "occurrences": 1,
      "last_seen": "2026-07-14T13:31:44.331Z"
    },
    {
      "id": "bug-011",
      "timestamp": "2026-07-14T15:04:50.167Z",
      "error_message": "Missing guard clause",
      "file": "lib/auth.ts",
      "root_cause": "No early return/throw for edge case: stores.length === 0",
      "fix": "Added guard clause: if (stores.length === 0)",
      "tags": [
        "auto-detected",
        "guard-clause",
        "ts"
      ],
      "related_bugs": [],
      "occurrences": 1,
      "last_seen": "2026-07-14T15:04:50.167Z"
    },
    {
      "id": "bug-012",
      "timestamp": "2026-07-14T15:39:59.303Z",
      "error_message": "Significant refactor of ",
      "file": "app/settings/page.tsx",
      "root_cause": "9 lines replaced/restructured",
      "fix": "Rewrote 23→15 lines (9 removed)",
      "tags": [
        "auto-detected",
        "refactor",
        "tsx"
      ],
      "related_bugs": [],
      "occurrences": 1,
      "last_seen": "2026-07-14T15:39:59.303Z"
    },
    {
      "id": "bug-013",
      "timestamp": "2026-07-14T15:42:00.168Z",
      "error_message": "Null/undefined access in ",
      "file": "lib/auth.ts",
      "root_cause": "Property access on potentially null/undefined value",
      "fix": "Added null safety (optional chaining or null check)",
      "tags": [
        "auto-detected",
        "null-safety",
        "ts"
      ],
      "related_bugs": [],
      "occurrences": 1,
      "last_seen": "2026-07-14T15:42:00.168Z"
    },
    {
      "id": "bug-014",
      "timestamp": "2026-07-14T15:43:04.104Z",
      "error_message": "Type error",
      "file": "app/admin/users/page.tsx",
      "root_cause": "Missing or incorrect type annotation",
      "fix": "Added type assertion/annotation",
      "tags": [
        "auto-detected",
        "type-fix",
        "tsx"
      ],
      "related_bugs": [],
      "occurrences": 1,
      "last_seen": "2026-07-14T15:43:04.104Z"
    },
    {
      "id": "bug-015",
      "timestamp": "2026-07-14T16:27:48.018Z",
      "error_message": "Significant refactor of ",
      "file": "app/admin/users/page.tsx",
      "root_cause": "4 lines replaced/restructured",
      "fix": "Rewrote 20→29 lines (4 removed)",
      "tags": [
        "auto-detected",
        "refactor",
        "tsx"
      ],
      "related_bugs": [],
      "occurrences": 1,
      "last_seen": "2026-07-14T16:27:48.018Z"
    },
    {
      "id": "bug-016",
      "timestamp": "2026-07-14T16:31:17.008Z",
      "error_message": "CSS fix: chevron, transition",
      "file": "app/globals.css",
      "root_cause": "chevron: rotates when the card is open. */ → rotates when the card is open.; transition: rotate 150ms ease → transform 150ms ease",
      "fix": "Changed chevron: rotates when the card is open. */ → rotates when the card is open.; transition: rotate 150ms ease → transform 150ms ease",
      "tags": [
        "auto-detected",
        "style-fix",
        "css"
      ],
      "related_bugs": [],
      "occurrences": 1,
      "last_seen": "2026-07-14T16:31:17.008Z"
    },
    {
      "id": "bug-017",
      "timestamp": "2026-07-15T09:38:17.832Z",
      "error_message": "Null/undefined access in ",
      "file": "app/admin/users/page.tsx",
      "root_cause": "Property access on potentially null/undefined value",
      "fix": "Added null safety (optional chaining or null check)",
      "tags": [
        "auto-detected",
        "null-safety",
        "tsx"
      ],
      "related_bugs": [],
      "occurrences": 1,
      "last_seen": "2026-07-15T09:38:17.832Z"
    },
    {
      "id": "bug-018",
      "timestamp": "2026-07-15T10:01:36.707Z",
      "error_message": "Wrong return value",
      "file": "lib/scan.ts",
      "root_cause": "Was returning: await db.$transaction(",
      "fix": "Now returns: { ...committed, message };",
      "tags": [
        "auto-detected",
        "return-value",
        "ts"
      ],
      "related_bugs": [],
      "occurrences": 1,
      "last_seen": "2026-07-15T10:01:36.707Z"
    },
    {
      "id": "bug-019",
      "timestamp": "2026-07-15T10:01:54.999Z",
      "error_message": "Missing guard clause",
      "file": "lib/scan.ts",
      "root_cause": "No early return/throw for edge case: err instanceof Prisma.PrismaClientKnownRequestError &&\n     ",
      "fix": "Added guard clause: if (err instanceof Prisma.PrismaClientKnownR)",
      "tags": [
        "auto-detected",
        "guard-clause",
        "ts"
      ],
      "related_bugs": [],
      "occurrences": 1,
      "last_seen": "2026-07-15T10:01:54.999Z"
    },
    {
      "id": "bug-020",
      "timestamp": "2026-07-15T10:03:31.342Z",
      "error_message": "Null/undefined access in ",
      "file": "app/api/scan/route.ts",
      "root_cause": "Property access on potentially null/undefined value",
      "fix": "Added null safety (optional chaining or null check)",
      "tags": [
        "auto-detected",
        "null-safety",
        "ts"
      ],
      "related_bugs": [],
      "occurrences": 1,
      "last_seen": "2026-07-15T10:03:31.342Z"
    },
    {
      "id": "bug-021",
      "timestamp": "2026-07-15T10:04:02.082Z",
      "error_message": "CSS fix: ok",
      "file": "app/scanner/scanner-client.tsx",
      "root_cause": "ok: false, message: 'Network error — please try again' → false, error: 'Network error — please try again'",
      "fix": "Changed ok: false, message: 'Network error — please try again' → false, error: 'Network error — please try again'",
      "tags": [
        "auto-detected",
        "style-fix",
        "tsx"
      ],
      "related_bugs": [],
      "occurrences": 1,
      "last_seen": "2026-07-15T10:04:02.082Z"
    },
    {
      "id": "bug-022",
      "timestamp": "2026-07-15T11:00:44.501Z",
      "error_message": "Significant refactor of ",
      "file": "app/api/webhook/route.ts",
      "root_cause": "2 lines replaced/restructured",
      "fix": "Rewrote 13→28 lines (2 removed)",
      "tags": [
        "auto-detected",
        "refactor",
        "ts"
      ],
      "related_bugs": [],
      "occurrences": 1,
      "last_seen": "2026-07-15T11:00:44.501Z"
    },
    {
      "id": "bug-023",
      "timestamp": "2026-07-15T11:48:35.409Z",
      "error_message": "Missing await",
      "file": "app/api/webhook/route.ts",
      "root_cause": "Async call without await — returned Promise instead of value",
      "fix": "Added await to async call",
      "tags": [
        "auto-detected",
        "async-fix",
        "ts"
      ],
      "related_bugs": [],
      "occurrences": 1,
      "last_seen": "2026-07-15T11:48:35.409Z"
    },
    {
      "id": "bug-024",
      "timestamp": "2026-07-15T11:48:45.956Z",
      "error_message": "Missing error handling in function",
      "file": "app/api/webhook/route.ts",
      "root_cause": "Code path had no error handling — exceptions would propagate uncaught",
      "fix": "Added try/catch block",
      "tags": [
        "auto-detected",
        "error-handling",
        "ts"
      ],
      "related_bugs": [],
      "occurrences": 1,
      "last_seen": "2026-07-15T11:48:45.956Z"
    },
    {
      "id": "bug-025",
      "timestamp": "2026-07-15T11:48:56.551Z",
      "error_message": "Significant refactor of ",
      "file": "app/settings/actions.ts",
      "root_cause": "2 lines replaced/restructured",
      "fix": "Rewrote 6→13 lines (2 removed)",
      "tags": [
        "auto-detected",
        "refactor",
        "ts"
      ],
      "related_bugs": [],
      "occurrences": 1,
      "last_seen": "2026-07-15T11:48:56.551Z"
    },
    {
      "id": "bug-026",
      "timestamp": "2026-07-15T11:49:10.498Z",
      "error_message": "Significant refactor of ",
      "file": "app/settings/page.tsx",
      "root_cause": "26 lines replaced/restructured",
      "fix": "Rewrote 29→15 lines (26 removed)",
      "tags": [
        "auto-detected",
        "refactor",
        "tsx"
      ],
      "related_bugs": [],
      "occurrences": 1,
      "last_seen": "2026-07-15T11:49:10.498Z"
    },
    {
      "id": "bug-027",
      "timestamp": "2026-07-15T14:40:44.587Z",
      "error_message": "Significant refactor of ",
      "file": "app/receipts/page.tsx",
      "root_cause": "9 lines replaced/restructured",
      "fix": "Rewrote 11→6 lines (9 removed)",
      "tags": [
        "auto-detected",
        "refactor",
        "tsx"
      ],
      "related_bugs": [],
      "occurrences": 1,
      "last_seen": "2026-07-15T14:40:44.587Z"
    },
    {
      "id": "bug-028",
      "timestamp": "2026-07-15T14:46:33.712Z",
      "error_message": "CSS fix: take",
      "file": "app/contacts/page.tsx",
      "root_cause": "take: PAGE_LIMIT, → PER_PAGE,",
      "fix": "Changed take: PAGE_LIMIT, → PER_PAGE,",
      "tags": [
        "auto-detected",
        "style-fix",
        "tsx"
      ],
      "related_bugs": [],
      "occurrences": 4,
      "last_seen": "2026-07-15T14:48:13.096Z"
    },
    {
      "id": "bug-029",
      "timestamp": "2026-07-15T14:49:05.418Z",
      "error_message": "Wrong reference: 100 should be 5",
      "file": "app/raffle/page.tsx",
      "root_cause": "Used \"100\" instead of \"5\"",
      "fix": "Changed 100 → 5",
      "tags": [
        "auto-detected",
        "wrong-reference",
        "tsx"
      ],
      "related_bugs": [],
      "occurrences": 1,
      "last_seen": "2026-07-15T14:49:05.419Z"
    },
    {
      "id": "bug-030",
      "timestamp": "2026-07-16T09:38:39.251Z",
      "error_message": "Incorrect value in code",
      "file": "app/contacts/page.tsx",
      "root_cause": "Had '@prisma/client'",
      "fix": "Changed to '@/lib/datetime'",
      "tags": [
        "auto-detected",
        "wrong-value",
        "tsx"
      ],
      "related_bugs": [],
      "occurrences": 3,
      "last_seen": "2026-07-16T09:38:57.732Z"
    },
    {
      "id": "bug-031",
      "timestamp": "2026-07-16T09:39:05.827Z",
      "error_message": "Incorrect value in code",
      "file": "app/api/export/route.ts",
      "root_cause": "Had '@prisma/client'",
      "fix": "Changed to '@/lib/datetime'",
      "tags": [
        "auto-detected",
        "wrong-value",
        "ts"
      ],
      "related_bugs": [],
      "occurrences": 2,
      "last_seen": "2026-07-16T09:39:31.955Z"
    },
    {
      "id": "bug-032",
      "timestamp": "2026-07-16T09:39:10.040Z",
      "error_message": "Wrong return value",
      "file": "app/api/export/route.ts",
      "root_cause": "Was returning: d ? d.toISOString() : '';",
      "fix": "Now returns: formatDateTimeCsv(d);",
      "tags": [
        "auto-detected",
        "return-value",
        "ts"
      ],
      "related_bugs": [],
      "occurrences": 1,
      "last_seen": "2026-07-16T09:39:10.040Z"
    },
    {
      "id": "bug-033",
      "timestamp": "2026-07-16T09:39:17.810Z",
      "error_message": "Wrong reference: fmtDate should be formatDateTimeCsv",
      "file": "app/api/export/route.ts",
      "root_cause": "Used \"fmtDate\" instead of \"formatDateTimeCsv\"",
      "fix": "Changed fmtDate → formatDateTimeCsv",
      "tags": [
        "auto-detected",
        "wrong-reference",
        "ts"
      ],
      "related_bugs": [],
      "occurrences": 2,
      "last_seen": "2026-07-16T09:39:20.800Z"
    },
    {
      "id": "bug-034",
      "timestamp": "2026-07-16T09:40:00.000Z",
      "error_message": "User: 'the time captured in the invoices is incorrect it could be because it's not adding +3 for bahrain time zone'",
      "file": "lib/datetime.ts",
      "root_cause": "Display-only bug; storage was already correct. Verified: Postgres TimeZone=GMT, receipts.created_at is 'timestamp without time zone', and JS now() vs PG now() drift measured 0.8s — so timestamps are stored in clean UTC. The pages (contacts/receipts/raffle) are SERVER components, so Date.toLocaleString() with no explicit zone formats in the SERVER's timezone, which is UTC on Vercel. Every invoice therefore rendered 3 hours early in production. It looked correct in local dev ONLY because the dev machine's zone is Asia/Bahrain, so the bug could never reproduce locally. The CSV export shared the fault via toISOString() (UTC by definition), and the export filename used toISOString().slice(0,10), which stamps yesterday's date between 00:00-03:00 Bahrain.",
      "fix": "Added lib/datetime.ts exposing formatDateTime / formatDateTimeCsv / todayInBahrain, all passing timeZone:'Asia/Bahrain' explicitly to module-level Intl.DateTimeFormat instances (hourCycle:'h23' so midnight renders 00:00, not 24:00). Replaced every toLocaleString()/toISOString() in app/contacts/page.tsx, app/receipts/page.tsx, app/raffle/page.tsx and app/api/export/route.ts; deleted the now-redundant fmtDate helper. CSV headers relabelled 'Timestamp (Bahrain)' / 'Last Seen (Bahrain)' since cells are no longer ISO/UTC. No data migration required. Verified by running the real formatter against real DB rows under TZ=UTC: IN-000545 went from '7/15/2026, 11:35:11 AM' to '15/07/2026, 14:35'. 9 unit tests in lib/datetime.test.ts pass identically under TZ=UTC, TZ=Asia/Bahrain and TZ=America/New_York.",
      "tags": [
        "timezone",
        "bahrain",
        "utc",
        "server-component",
        "date-formatting",
        "vercel",
        "prod-only",
        "csv-export"
      ],
      "related_bugs": [
        "bug-031",
        "bug-032",
        "bug-033"
      ],
      "occurrences": 1,
      "last_seen": "2026-07-16T09:40:00.000Z"
    },
    {
      "id": "bug-035",
      "timestamp": "2026-07-16T10:15:00.000Z",
      "error_message": "Security audit finding #2: sign-in had no brute-force protection — unlimited bcrypt.compare attempts per second, no lockout, no rate limit, and no log that an attack was happening.",
      "file": "auth.ts",
      "root_cause": "authorize() in auth.ts looked up the user and compared the password with no attempt counter of any kind. A public portal + password auth + no lockout = credential stuffing works and leaves no trace. Two related holes in the same function: an unknown email returned before bcrypt ran, so response time (~900ms vs instant) enumerated the staff list (audit finding #9); and the bcrypt cost 10 was copy-pasted at three call sites (auth.ts, admin/users/actions.ts, prisma/seed.ts) so it could drift.",
      "fix": "Added login_attempts table (migration 0003) counting failures per email and per IP. lib/login-throttle.ts holds the pure policy (email: 5 failures → lock, doubling 1→2→4→8→15 min cap; IP: 30 failures, deliberately loose because a shop's cashiers share one NAT and locking the store mid-shift stops them scanning). lib/login-attempts.ts holds the Postgres reads/writes plus opportunistic GC. auth.ts throws a CredentialsSignin subclass whose code carries the wait ('too_many_attempts:60'), which the sign-in form renders as a human message. Enumeration closed via lib/password.ts ABSENT_USER_HASH — a bcrypt hash of an unrecorded random value, compared against when the email is unknown so the timing matches. BCRYPT_COST now defined once and shared. Failed sign-ins are console.warn'd.",
      "tags": [
        "security",
        "auth",
        "brute-force",
        "rate-limit",
        "lockout",
        "user-enumeration",
        "timing-attack",
        "bcrypt",
        "nextauth"
      ],
      "related_bugs": [],
      "occurrences": 1,
      "last_seen": "2026-07-16T10:15:00.000Z"
    },
    {
      "id": "bug-036",
      "timestamp": "2026-07-16T10:45:00.000Z",
      "error_message": "Security audit finding #3: the webhook failed OPEN — if no app secret could be resolved, signature verification silently switched off and /api/webhook accepted anything from anyone.",
      "file": "app/api/webhook/route.ts",
      "root_cause": "lib/webhook.ts verifySignatureAgainstAny() began `if (appSecrets.length === 0) return true` — documented and unit-tested as 'verification off'. getAppSecrets() built that list from META_APP_SECRET plus each store's decrypted secret, and a decrypt failure only logged and continued. So a wrong/rotated ENCRYPTION_KEY, or a restored DB, emptied the list and turned verification off — precisely when it mattered most. The insecure state was indistinguishable from the secure one in the logs.",
      "fix": "Removed the fail-open entirely; there is no 'no secrets = allow' path and no insecure escape hatch. The route now resolves candidate secrets for the phone_number_id the payload names: none resolvable -> 503 (our misconfiguration, so Meta retries and the events can still land once Settings/ENCRYPTION_KEY are fixed); signature mismatch -> 403. Decrypt failure logs loudly and yields no candidate rather than skipping verification. Every rejection names what to fix.",
      "tags": [
        "security",
        "webhook",
        "fail-open",
        "signature",
        "meta",
        "hmac",
        "encryption-key"
      ],
      "related_bugs": [
        "bug-037"
      ],
      "occurrences": 1,
      "last_seen": "2026-07-16T10:45:00.000Z"
    },
    {
      "id": "bug-037",
      "timestamp": "2026-07-16T10:45:00.000Z",
      "error_message": "Security audit finding #4: one store could forge the other store's WhatsApp delivery statuses. The two stores are legally separate companies sharing one webhook URL.",
      "file": "app/api/webhook/route.ts",
      "root_cause": "verifySignatureAgainstAny() returned a BOOLEAN — it discarded which secret matched, which is exactly the fact needed to scope the events. A payload signed by ANY store's app was accepted, then applyStatusEvent() looked the receipt up by wamid ALONE (db.receipt.findFirst({ where: { wamid } })) with no store scoping. Each store's manager sets their own app secret in Settings, so Morslon could sign a body carrying Modern Sources' wamids and rewrite their receipts.",
      "fix": "Replaced verifySignatureAgainstAny with findSigner(), which returns the matching candidate rather than a boolean. The route resolves the store from metadata.phone_number_id (safe to read unverified: it only picks WHICH secret to check, and a lie fails verification), verifies against that store's secret only, then applies two layers: (1) any change whose phone_number_id != the signer's is refused as cross-store, blocking a mixed body signed by one app; (2) the receipt lookup is scoped { wamid, storeId: signer.store.id }, so a wamid alone is not proof of ownership. logIncomingMessage now uses the signing store instead of a second phone lookup. CAVEAT: while two stores share the META_APP_SECRET env fallback they can still sign for each other — per-store secrets in Settings are what make the isolation real.",
      "fix_verified": "Sent a real morslon-signed body smuggling a change for another phone_number_id carrying receipt IN-00087's real wamid marked 'failed' (failed always wins over 'read', so it would have been visible). IN-00087 stayed 'read' with no error. Also confirmed on real data that the same wamid resolves under morslon but is not found under modern-sources.",
      "tags": [
        "security",
        "webhook",
        "multi-tenant",
        "store-isolation",
        "forgery",
        "wamid",
        "meta"
      ],
      "related_bugs": [
        "bug-036"
      ],
      "occurrences": 1,
      "last_seen": "2026-07-16T10:45:00.000Z"
    },
    {
      "id": "bug-049",
      "timestamp": "2026-07-16T10:55:51.570Z",
      "error_message": "Type error",
      "file": "app/api/scan/route.ts",
      "root_cause": "Missing or incorrect type annotation",
      "fix": "Added type assertion/annotation",
      "tags": [
        "auto-detected",
        "type-fix",
        "ts"
      ],
      "related_bugs": [],
      "occurrences": 1,
      "last_seen": "2026-07-16T10:55:51.570Z"
    },
    {
      "id": "bug-050",
      "timestamp": "2026-07-16T10:56:28.132Z",
      "error_message": "Significant refactor of ",
      "file": "lib/store-lock.test.ts",
      "root_cause": "2 lines replaced/restructured",
      "fix": "Rewrote 3→4 lines (2 removed)",
      "tags": [
        "auto-detected",
        "refactor",
        "ts"
      ],
      "related_bugs": [],
      "occurrences": 1,
      "last_seen": "2026-07-16T10:56:28.132Z"
    },
    {
      "id": "bug-051",
      "timestamp": "2026-07-16T10:57:01.553Z",
      "error_message": "Incorrect value in code",
      "file": "lib/store-lock.test.ts",
      "root_cause": "Had './scan'",
      "fix": "Changed to './store-lock'",
      "tags": [
        "auto-detected",
        "wrong-value",
        "ts"
      ],
      "related_bugs": [],
      "occurrences": 1,
      "last_seen": "2026-07-16T10:57:01.553Z"
    },
    {
      "id": "bug-038",
      "timestamp": "2026-07-16T11:15:00.000Z",
      "error_message": "RACE_CONDITION_HANDLING.md as written would have shipped an advisory lock that protected nothing: it specified pg_advisory_xact_lock() but left the transaction at Serializable.",
      "file": "lib/scan.ts",
      "root_cause": "Under SERIALIZABLE (and REPEATABLE READ) Postgres freezes the transaction snapshot at the FIRST statement — which, with this pattern, is the lock acquisition itself. The snapshot is taken before the function blocks. So a scan that queues on the lock acquires it and then still reads the world as it was BEFORE the winner committed: MAX(entry_number) comes back stale and it allocates a duplicate entry number anyway. The lock appears to work while doing nothing. READ COMMITTED takes a fresh snapshot per statement, so reads after the lock is granted see the previous scan's committed rows.",
      "fix": "Switched the scan transaction to Prisma.TransactionIsolationLevel.ReadCommitted and took the advisory lock as the first statement inside it. Proved empirically: two txns contending for the same key, A inserts+commits while B waits — under Serializable B counted 0 after acquiring the lock (1 was committed); under ReadCommitted B counted 1.",
      "tags": [
        "race-condition",
        "postgres",
        "advisory-lock",
        "isolation-level",
        "snapshot",
        "serializable",
        "read-committed",
        "spec-bug"
      ],
      "related_bugs": [
        "bug-039"
      ],
      "occurrences": 1,
      "last_seen": "2026-07-16T11:15:00.000Z"
    },
    {
      "id": "bug-039",
      "timestamp": "2026-07-16T11:15:00.000Z",
      "error_message": "Raw query failed. Code: `N/A`. Message: `Failed to deserialize column of type 'void'` / DriverAdapterError: UnsupportedNativeDataType { kind: 'UnsupportedNativeDataType', type: 'void' } — every scan failed with P2010.",
      "file": "lib/scan.ts",
      "root_cause": "Took the advisory lock with tx.$queryRaw`SELECT pg_advisory_xact_lock(...)`. pg_advisory_xact_lock() returns void, and $queryRaw tries to deserialize the result columns; the @prisma/adapter-neon driver cannot map Postgres 'void'. RACE_CONDITION_HANDLING.md actually had this right with $executeRaw — I 'corrected' it to $queryRaw on the reasoning that SELECT belongs in $queryRaw, and broke every scan.",
      "fix": "Use tx.$executeRaw for the lock: it only reports a row count and never deserializes columns, so the void return is fine. Caught immediately by the concurrency test (0/5 scans succeeded) — it would have taken down every scan in production.",
      "tags": [
        "prisma",
        "neon-adapter",
        "raw-query",
        "void",
        "advisory-lock",
        "executeRaw",
        "queryRaw"
      ],
      "related_bugs": [
        "bug-038"
      ],
      "occurrences": 1,
      "last_seen": "2026-07-16T11:15:00.000Z"
    },
    {
      "id": "bug-040",
      "timestamp": "2026-07-16T11:15:00.000Z",
      "error_message": "A raffle entry-number collision returned HTTP 500 \"Something went wrong while logging the scan\" and lost the scan, instead of retrying.",
      "file": "lib/scan.ts",
      "root_cause": "The P2002 handler only mapped the violation to a clean error when err.meta.target included 'invoice'; anything else — realistically the (store_id, entry_number) unique index — fell through to `throw err` and surfaced as a 500. Only P2034 was retried.",
      "fix": "Retry non-invoice P2002 within maxAttempts (re-reads MAX(entry_number) and takes the next free number). Also stopped retrying ScanError itself — a genuine duplicate invoice was being re-attempted three times — and mapped statement_timeout (SQLSTATE 57014) to a friendly ScanError('System busy, please try again', 'busy') -> HTTP 503 rather than a raw 500.",
      "tags": [
        "race-condition",
        "error-handling",
        "prisma",
        "p2002",
        "retry",
        "http-status"
      ],
      "related_bugs": [
        "bug-038"
      ],
      "occurrences": 1,
      "last_seen": "2026-07-16T11:15:00.000Z"
    },
    {
      "id": "bug-052",
      "timestamp": "2026-07-16T14:48:11.030Z",
      "error_message": "Type error",
      "file": "app/settings/page.tsx",
      "root_cause": "Missing or incorrect type annotation",
      "fix": "Added type assertion/annotation",
      "tags": [
        "auto-detected",
        "type-fix",
        "tsx"
      ],
      "related_bugs": [],
      "occurrences": 1,
      "last_seen": "2026-07-16T14:48:11.030Z"
    },
    {
      "id": "bug-041",
      "timestamp": "2026-07-16T15:00:00.000Z",
      "error_message": "User: 'is the connector to google spreadsheet work?' — Settings showed a 'Sheet ID (optional)' field that saved fine and did absolutely nothing.",
      "file": "app/settings/page.tsx",
      "root_cause": "The Google Sheets integration was never built, but the UI implied it was. stores.google_sheet_id was written by the settings form and never read by anything; no google library was in package.json; GOOGLE_SERVICE_ACCOUNT_* appeared only in .env.example and were read nowhere. A manager could paste a real sheet ID, get 'Settings saved', and believe their data was being backed up when nothing was ever written.",
      "fix": "Built the weekly backup for real: lib/google-sheets.ts (service-account JWT signed with node:crypto + Sheets REST, no googleapis SDK — it is huge and would tax every cold start), lib/backup.ts (row building + never-shrink guard), app/api/cron/backup/route.ts (CRON_SECRET-authenticated, per-store, one store's failure cannot stop the other), vercel.json weekly schedule, /api/cron made public in auth.config.ts. Relabelled the field 'Weekly backup (Google Sheets)' with a hint explaining what it does and that the sheet must be shared with the service account.",
      "tags": [
        "google-sheets",
        "backup",
        "dead-ui",
        "misleading-ux",
        "cron",
        "vercel",
        "jwt",
        "unbuilt-feature"
      ],
      "related_bugs": [],
      "occurrences": 1,
      "last_seen": "2026-07-16T15:00:00.000Z"
    },
    {
      "id": "bug-053",
      "timestamp": "2026-07-16T15:44:14.565Z",
      "error_message": "CSS fix: href",
      "file": "components/app-nav.tsx",
      "root_cause": "href: '/admin/users', label: 'Users', roles: ['admin'] → '/admin/sheets', label: 'Sheets', roles: ['admin']",
      "fix": "Changed href: '/admin/users', label: 'Users', roles: ['admin'] → '/admin/sheets', label: 'Sheets', roles: ['admin']",
      "tags": [
        "auto-detected",
        "style-fix",
        "tsx"
      ],
      "related_bugs": [],
      "occurrences": 1,
      "last_seen": "2026-07-16T15:44:14.565Z"
    },
    {
      "id": "bug-054",
      "timestamp": "2026-07-16T15:44:35.219Z",
      "error_message": "Significant refactor of ",
      "file": "README.md",
      "root_cause": "12 lines replaced/restructured",
      "fix": "Rewrote 14→21 lines (12 removed)",
      "tags": [
        "auto-detected",
        "refactor",
        "md"
      ],
      "related_bugs": [],
      "occurrences": 1,
      "last_seen": "2026-07-16T15:44:35.219Z"
    },
    {
      "id": "bug-042",
      "timestamp": "2026-07-16T15:50:00.000Z",
      "error_message": "Google Sheets sync failed for every store: 'error:1E08010C:DECODER routines::unsupported'. User had set up the service account and redeployed, but nothing worked.",
      "file": ".env.local / Vercel env",
      "root_cause": "GOOGLE_SERVICE_ACCOUNT_PRIVATE_KEY held the service account JSON's `private_key_id` (a 40-char hex string) instead of its `private_key` (a ~1700-char PEM). Both fields sit next to each other in the downloaded JSON and the names are nearly identical. node:crypto's createSign could not parse it, so the JWT was never built and Google was never contacted. The same wrong value was in both .env.local and Vercel.",
      "fix": "Diagnosed by checking the value's shape rather than its contents: length 40, no -----BEGIN prefix, matches /^[0-9a-f]{40}$/ = private_key_id. User re-pasted the real private_key (1732 chars, signs fine). NOTE FOR FUTURE: a read-only probe (buildServiceAccountJwt + tabRowCount on each tab) verifies key + sharing + sheet id + tab names WITHOUT writing anything — always do that before running a sync that overwrites.",
      "tags": [
        "google-sheets",
        "service-account",
        "jwt",
        "private-key",
        "config-error",
        "env-vars"
      ],
      "related_bugs": [
        "bug-041"
      ],
      "occurrences": 1,
      "last_seen": "2026-07-16T15:50:00.000Z"
    },
    {
      "id": "bug-055",
      "timestamp": "2026-07-16T15:53:17.211Z",
      "error_message": "CSS fix: hover",
      "file": "app/admin/sheets/page.tsx",
      "root_cause": "hover: bg-amber-50 disabled:opacity-40 dark:border-amber-700 dark:text-amber-400 dark:hover:bg-amber-950/40\" → bg-black/[.04] disabled:opacity-40 dark:border-white/15 dark:hover:bg-white/[.06]\"",
      "fix": "Changed hover: bg-amber-50 disabled:opacity-40 dark:border-amber-700 dark:text-amber-400 dark:hover:bg-amber-950/40\" → bg-black/[.04] disabled:opacity-40 dark:border-white/15 dark:hover:bg-white/[.06]\"",
      "tags": [
        "auto-detected",
        "style-fix",
        "tsx"
      ],
      "related_bugs": [],
      "occurrences": 1,
      "last_seen": "2026-07-16T15:53:17.211Z"
    },
    {
      "id": "bug-056",
      "timestamp": "2026-07-16T15:53:23.694Z",
      "error_message": "Type error",
      "file": "app/admin/sheets/page.tsx",
      "root_cause": "Missing or incorrect type annotation",
      "fix": "Added type assertion/annotation",
      "tags": [
        "auto-detected",
        "type-fix",
        "tsx"
      ],
      "related_bugs": [],
      "occurrences": 1,
      "last_seen": "2026-07-16T15:53:23.694Z"
    },
    {
      "id": "bug-043",
      "timestamp": "2026-07-16T15:56:00.000Z",
      "error_message": "User: 'let's add a button to sync one store. maybe we don't want to sync both' — the admin Sheets page only offered all-or-nothing syncs.",
      "file": "app/admin/sheets/page.tsx",
      "root_cause": "The page shipped with only global 'Sync now' / 'Sync now (force)' buttons, so an admin could not refresh one company's sheet without also rewriting the other's. lib/sheets-sync.ts already exported a per-store syncStore(); nothing exposed it.",
      "fix": "Added syncOneStore(formData) server action (validates storeId against the DB, requireAdmin) and per-store 'Sync this store' + 'Force' buttons on each card. Buttons are disabled when the store has no Sheet ID or credentials are missing, rather than reporting 'skipped'. Global button reduced to 'Sync all stores' with NO force option — forcing lets a sheet shrink, so it should be decided one store at a time rather than applied to both companies in one click. Verified only the chosen store's sheet and last_sync_at change.",
      "tags": [
        "admin-ui",
        "google-sheets",
        "per-store",
        "store-isolation",
        "server-action"
      ],
      "related_bugs": [
        "bug-041",
        "bug-042"
      ],
      "occurrences": 1,
      "last_seen": "2026-07-16T15:56:00.000Z"
    },
    {
      "id": "bug-057",
      "timestamp": "2026-07-19T09:45:03.086Z",
      "error_message": "Wrong reference: EMAIL_POLICY should be ACCOUNT_POLICY",
      "file": "lib/login-throttle.ts",
      "root_cause": "Used \"EMAIL_POLICY\" instead of \"ACCOUNT_POLICY\"",
      "fix": "Changed EMAIL_POLICY → ACCOUNT_POLICY",
      "tags": [
        "auto-detected",
        "wrong-reference",
        "ts"
      ],
      "related_bugs": [],
      "occurrences": 2,
      "last_seen": "2026-07-19T09:45:14.486Z"
    },
    {
      "id": "bug-058",
      "timestamp": "2026-07-19T09:45:10.388Z",
      "error_message": "Significant refactor of ",
      "file": "lib/login-throttle.ts",
      "root_cause": "2 lines replaced/restructured",
      "fix": "Rewrote 6→14 lines (2 removed)",
      "tags": [
        "auto-detected",
        "refactor",
        "ts"
      ],
      "related_bugs": [],
      "occurrences": 1,
      "last_seen": "2026-07-19T09:45:10.388Z"
    },
    {
      "id": "bug-059",
      "timestamp": "2026-07-19T09:46:02.951Z",
      "error_message": "Wrong reference: cashierEmail should be cashierUsername",
      "file": "app/receipts/page.tsx",
      "root_cause": "Used \"cashierEmail\" instead of \"cashierUsername\"",
      "fix": "Changed cashierEmail → cashierUsername",
      "tags": [
        "auto-detected",
        "wrong-reference",
        "tsx"
      ],
      "related_bugs": [],
      "occurrences": 1,
      "last_seen": "2026-07-19T09:46:02.951Z"
    },
    {
      "id": "bug-060",
      "timestamp": "2026-07-19T09:46:10.924Z",
      "error_message": "Wrong reference: cashierEmail should be cashierUsername",
      "file": "app/api/export/route.ts",
      "root_cause": "Used \"cashierEmail\" instead of \"cashierUsername\"",
      "fix": "Changed cashierEmail → cashierUsername",
      "tags": [
        "auto-detected",
        "wrong-reference",
        "ts"
      ],
      "related_bugs": [],
      "occurrences": 1,
      "last_seen": "2026-07-19T09:46:10.924Z"
    },
    {
      "id": "bug-061",
      "timestamp": "2026-07-19T09:46:20.737Z",
      "error_message": "Null/undefined access in ",
      "file": "components/app-nav.tsx",
      "root_cause": "Property access on potentially null/undefined value",
      "fix": "Added null safety (optional chaining or null check)",
      "tags": [
        "auto-detected",
        "null-safety",
        "tsx"
      ],
      "related_bugs": [],
      "occurrences": 1,
      "last_seen": "2026-07-19T09:46:20.737Z"
    },
    {
      "id": "bug-062",
      "timestamp": "2026-07-19T09:46:49.107Z",
      "error_message": "Significant refactor of ",
      "file": "app/admin/users/page.tsx",
      "root_cause": "3 lines replaced/restructured",
      "fix": "Rewrote 6→8 lines (3 removed)",
      "tags": [
        "auto-detected",
        "refactor",
        "tsx"
      ],
      "related_bugs": [],
      "occurrences": 1,
      "last_seen": "2026-07-19T09:46:49.107Z"
    },
    {
      "id": "bug-063",
      "timestamp": "2026-07-19T09:46:57.075Z",
      "error_message": "Null/undefined access in ",
      "file": "app/admin/users/actions.ts",
      "root_cause": "Property access on potentially null/undefined value",
      "fix": "Added null safety (optional chaining or null check)",
      "tags": [
        "auto-detected",
        "null-safety",
        "ts"
      ],
      "related_bugs": [],
      "occurrences": 1,
      "last_seen": "2026-07-19T09:46:57.075Z"
    },
    {
      "id": "bug-064",
      "timestamp": "2026-07-19T09:47:09.972Z",
      "error_message": "Significant refactor of ",
      "file": "app/admin/users/actions.ts",
      "root_cause": "4 lines replaced/restructured",
      "fix": "Rewrote 39→50 lines (4 removed)",
      "tags": [
        "auto-detected",
        "refactor",
        "ts"
      ],
      "related_bugs": [],
      "occurrences": 1,
      "last_seen": "2026-07-19T09:47:09.972Z"
    },
    {
      "id": "bug-065",
      "timestamp": "2026-07-19T09:47:33.849Z",
      "error_message": "Incorrect value in code",
      "file": "prisma/seed.ts",
      "root_cause": "Had '\\nℹ No admin seeded. Set SEED_ADMIN_EMAIL and SEE",
      "fix": "Changed to '\\nℹ No admin seeded. Set SEED_ADMIN_USERNAME and ",
      "tags": [
        "auto-detected",
        "wrong-value",
        "ts"
      ],
      "related_bugs": [],
      "occurrences": 1,
      "last_seen": "2026-07-19T09:47:33.849Z"
    },
    {
      "id": "bug-066",
      "timestamp": "2026-07-19T09:47:43.087Z",
      "error_message": "Significant refactor of ",
      "file": "prisma/seed.ts",
      "root_cause": "2 lines replaced/restructured",
      "fix": "Rewrote 3→4 lines (2 removed)",
      "tags": [
        "auto-detected",
        "refactor",
        "ts"
      ],
      "related_bugs": [],
      "occurrences": 1,
      "last_seen": "2026-07-19T09:47:43.087Z"
    },
    {
      "id": "bug-067",
      "timestamp": "2026-07-19T09:48:44.788Z",
      "error_message": "Incorrect value in code",
      "file": "lib/login-throttle.test.ts",
      "root_cause": "Had 'tolerates far more failures from one IP than from",
      "fix": "Changed to 'tolerates far more failures from one IP than from",
      "tags": [
        "auto-detected",
        "wrong-value",
        "ts"
      ],
      "related_bugs": [],
      "occurrences": 2,
      "last_seen": "2026-07-19T09:48:57.536Z"
    },
    {
      "id": "bug-068",
      "timestamp": "2026-07-19T09:53:19.572Z",
      "error_message": "Incorrect value in code",
      "file": "README.md",
      "root_cause": "Had `SEED_ADMIN_EMAIL`",
      "fix": "Changed to `SEED_ADMIN_USERNAME`",
      "tags": [
        "auto-detected",
        "wrong-value",
        "md"
      ],
      "related_bugs": [],
      "occurrences": 2,
      "last_seen": "2026-07-19T09:53:24.525Z"
    },
    {
      "id": "bug-044",
      "timestamp": "2026-07-19T11:55:00.000Z",
      "error_message": "Sessions never meaningfully expired — a signed-in till stayed signed in for the NextAuth default 30 days (flagged in the security audit as a lower-severity finding).",
      "file": "auth.config.ts",
      "root_cause": "session was `{ strategy: 'jwt' }` with no maxAge, so the default 30-day token applied. A shared till left unattended, or a device taken home, stayed authenticated indefinitely. Firing someone did not end their session either — only deleting the profile did, via getCurrentUserProfile() returning null.",
      "fix": "session.maxAge = 2h with updateAge = 5min. maxAge alone would NOT slide: NextAuth only rewrites the token once updateAge has elapsed, so without it an active cashier would be logged out mid-shift at the 2h mark. Verified empirically: the issued cookie expires in exactly 2.00h (note: NextAuth sets `Expires`, NOT `Max-Age` — do not grep for Max-Age), and after 5m20s of activity the expiry moved forward 321s with the session still valid.",
      "tags": [
        "security",
        "auth",
        "session",
        "nextauth",
        "jwt",
        "expiry"
      ],
      "related_bugs": [],
      "occurrences": 1,
      "last_seen": "2026-07-19T11:55:00.000Z"
    },
    {
      "id": "bug-045",
      "timestamp": "2026-07-19T11:55:00.000Z",
      "error_message": "User: 'lets use user name instead of emails' — staff had to sign in with an email address they mostly do not have.",
      "file": "prisma/schema.prisma",
      "root_cause": "UserProfile had a required unique email used as the login credential. Retail till staff rarely have a work email, so accounts were being given synthetic addresses (cashier1@morslon.com) that nobody could remember or type quickly on a shared device.",
      "fix": "Migration 0005: added unique `username`, backfilled from the email local-part (admin@morslon.com -> admin), made `email` nullable, renamed receipts.cashier_email -> cashier_username. Order matters: add the column NULLABLE, backfill, THEN set NOT NULL — adding NOT NULL to a populated table fails outright. Postgres allows many NULLs under a unique index, so email stays unique without blocking accounts that have none. Switched authorize() to look up by username, renamed the throttle key prefix email: -> user: (ACCOUNT_KEY_PREFIX, shared so login-attempts.ts cannot drift), updated the sign-in form, admin create/edit/search, nav, receipts column, CSV header and the seed script (SEED_ADMIN_USERNAME). Usernames are normalized lowercase and validated /^[a-z0-9._-]{3,32}$/.",
      "tags": [
        "auth",
        "username",
        "migration",
        "prisma",
        "not-null-backfill",
        "schema-change"
      ],
      "related_bugs": [
        "bug-044"
      ],
      "occurrences": 1,
      "last_seen": "2026-07-19T11:55:00.000Z"
    },
    {
      "id": "bug-069",
      "timestamp": "2026-07-19T13:09:12.474Z",
      "error_message": "Type error",
      "file": "lib/google-sheets.ts",
      "root_cause": "Missing or incorrect type annotation",
      "fix": "Added type assertion/annotation",
      "tags": [
        "auto-detected",
        "type-fix",
        "ts"
      ],
      "related_bugs": [],
      "occurrences": 1,
      "last_seen": "2026-07-19T13:09:12.474Z"
    },
    {
      "id": "bug-070",
      "timestamp": "2026-07-19T13:12:09.915Z",
      "error_message": "Type error",
      "file": "app/api/export/route.ts",
      "root_cause": "Missing or incorrect type annotation",
      "fix": "Added type assertion/annotation",
      "tags": [
        "auto-detected",
        "type-fix",
        "ts"
      ],
      "related_bugs": [],
      "occurrences": 1,
      "last_seen": "2026-07-19T13:12:09.915Z"
    },
    {
      "id": "bug-046",
      "timestamp": "2026-07-19T16:15:00.000Z",
      "error_message": "CSV export silently truncated at 10,000 rows. The prize draw is run off exported data, so entries beyond 10k could never win and nothing said so.",
      "file": "app/api/export/route.ts",
      "root_cause": "MAX_ROWS = 10000 was a hard `take:` on every export query, with all rows buffered in memory and joined into one string. At 50k raffle entries the file contained 10k rows and no warning; at 300k it dropped 290k. Modelled from real row shapes, not guessed.",
      "fix": "Removed the cap entirely and switched to a ReadableStream that pages the DB (PAGE_SIZE 5000) while the browser downloads, so memory is flat regardless of size. Paging is by id CURSOR, not skip/offset, which degrades badly past ~100k. Every orderBy now ends with `{ id: 'asc' }` so the ordering is total — rows sharing a timestamp cannot shuffle between pages and get duplicated or skipped. A mid-stream failure appends an 'EXPORT FAILED — this file is incomplete' row, because the 200 status is already sent and a short file would otherwise look complete. Verified end-to-end: 25,000 entries exported in 4.7s, entry 1 through 25,000, no gaps.",
      "tags": [
        "export",
        "csv",
        "silent-truncation",
        "streaming",
        "cursor-pagination",
        "scale",
        "draw-integrity"
      ],
      "related_bugs": [
        "bug-047"
      ],
      "occurrences": 1,
      "last_seen": "2026-07-19T16:15:00.000Z"
    },
    {
      "id": "bug-047",
      "timestamp": "2026-07-19T16:15:00.000Z",
      "error_message": "The nightly Google Sheets sync would have started failing partway through the campaign: it wrote each tab in ONE request, which Google rejects or times out on past roughly 50k rows.",
      "file": "lib/google-sheets.ts",
      "root_cause": "overwriteTab() PUT the entire values array in a single request. Measured payload sizes from real row shapes: 50k entries = 4.3 MB, 100k = 8.6 MB, 300k = 25.9 MB. The user confirmed the PRIZE DRAW IS RUN OFF THE SHEET, so a failed or stale sync means entries missing from the draw — this was draw integrity, not just a performance issue. (Google's 10M cell limit is further out, ~2M cells at 300k entries, so request size bites first.)",
      "fix": "Write in ROWS_PER_REQUEST = 10,000 chunks at computed A1 offsets (A1, A10001, A20001...). Batches go top-down and the large tabs are append-only in a stable order (raffle by entryNumber, log by createdAt), so a failure partway leaves earlier rows correct and later ones stale — never scrambled — and the next sync repairs it. The trim of leftover rows still runs afterwards. Unit-tested with a stubbed fetch: 300k rows becomes exactly 30 requests, none over 10k, every row written once, offsets contiguous.",
      "tags": [
        "google-sheets",
        "batching",
        "scale",
        "draw-integrity",
        "payload-limit",
        "cron"
      ],
      "related_bugs": [
        "bug-046"
      ],
      "occurrences": 1,
      "last_seen": "2026-07-19T16:15:00.000Z"
    },
    {
      "id": "bug-071",
      "timestamp": "2026-07-19T14:10:25.739Z",
      "error_message": "Significant refactor of ",
      "file": "app/globals.css",
      "root_cause": "2 lines replaced/restructured",
      "fix": "Rewrote 25→45 lines (2 removed)",
      "tags": [
        "auto-detected",
        "refactor",
        "css"
      ],
      "related_bugs": [],
      "occurrences": 1,
      "last_seen": "2026-07-19T14:10:25.739Z"
    },
    {
      "id": "bug-072",
      "timestamp": "2026-07-19T14:11:41.222Z",
      "error_message": "Significant refactor of ",
      "file": "app/sign-in/page.tsx",
      "root_cause": "4 lines replaced/restructured",
      "fix": "Rewrote 20→27 lines (4 removed)",
      "tags": [
        "auto-detected",
        "refactor",
        "tsx"
      ],
      "related_bugs": [],
      "occurrences": 1,
      "last_seen": "2026-07-19T14:11:41.222Z"
    },
    {
      "id": "bug-048",
      "timestamp": "2026-07-19T14:30:00.000Z",
      "error_message": "User: 'add dark/light theme mode' — the app followed the OS via prefers-color-scheme with no way to override it.",
      "file": "app/globals.css",
      "root_cause": "Dark mode existed but was entirely OS-driven: globals.css used @media (prefers-color-scheme: dark) and every component uses Tailwind `dark:` utilities, which in Tailwind v4 also follow prefers-color-scheme by default. A toggle that only swapped the CSS variables would have left every `dark:border-white/10` in the app still obeying the OS — the two would visibly disagree.",
      "fix": "Drive the theme from a `data-theme` attribute on <html> and redirect Tailwind's variant at it with `@custom-variant dark (&:where([data-theme=\"dark\"], [data-theme=\"dark\"] *))`. localStorage holds the PREFERENCE (light|dark|system); data-theme holds the RESOLVED value and is always concrete, so the CSS never reasons about 'system'. A blocking inline <script> in <head> (components/theme-script.tsx) applies it before first paint — anything waiting on React would paint the wrong theme first. <html suppressHydrationWarning> because the script legitimately changes the attribute before hydration; the toggle starts as 'system' on both server and client and reads localStorage in an effect, so no marker flashes as active. matchMedia listener keeps 'system' live without a reload. Toggle added to the nav AND the sign-in page, which has no nav.",
      "fix_verified": "In-browser with computed styles: OS prefers dark, clicked Light -> data-theme=light, body #fff, and a `dark:border-white/15` input border flipped to black/0.1, proving the Tailwind variant follows the attribute not the OS. Survived reload (script in <head>). System restored OS-following. No hydration warnings in console.",
      "tags": [
        "ui",
        "theme",
        "dark-mode",
        "tailwind-v4",
        "custom-variant",
        "fouc",
        "hydration",
        "localstorage"
      ],
      "related_bugs": [],
      "occurrences": 1,
      "last_seen": "2026-07-19T14:30:00.000Z"
    },
    {
      "id": "bug-073",
      "timestamp": "2026-07-19T16:07:37.768Z",
      "error_message": "Incorrect value in code",
      "file": "app/scanner/scanner-client.tsx",
      "root_cause": "Had \"SI-100008 | HASSAN MAHMOOD | +97333959565 | 45,50",
      "fix": "Changed to \"off\"",
      "tags": [
        "auto-detected",
        "wrong-value",
        "tsx"
      ],
      "related_bugs": [],
      "occurrences": 1,
      "last_seen": "2026-07-19T16:07:37.768Z"
    }
  ]
}